trello/__init__.py
trello/api_helper.py
trello/configuration.py
trello/trello_client.py
trello/controllers/__init__.py
trello/controllers/action_controller.py
trello/controllers/base_controller.py
trello/controllers/batch_controller.py
trello/controllers/board_controller.py
trello/controllers/card_controller.py
trello/controllers/checklist_controller.py
trello/controllers/label_controller.py
trello/controllers/list_controller.py
trello/controllers/member_controller.py
trello/controllers/notification_controller.py
trello/controllers/organization_controller.py
trello/controllers/search_controller.py
trello/controllers/session_controller.py
trello/controllers/token_controller.py
trello/controllers/type_controller.py
trello/controllers/webhook_controller.py
trello/exceptions/__init__.py
trello/exceptions/api_exception.py
trello/http/__init__.py
trello/http/http_call_back.py
trello/http/http_method_enum.py
trello/http/http_request.py
trello/http/http_response.py
trello/http/auth/__init__.py
trello/http/auth/api_key.py
trello/http/auth/api_token.py
trello/models/__init__.py
trello/models/actions.py
trello/models/actions_comments.py
trello/models/actions_text.py
trello/models/boards.py
trello/models/boards_checklists.py
trello/models/boards_closed.py
trello/models/boards_desc.py
trello/models/boards_id_organization.py
trello/models/boards_labels.py
trello/models/boards_lists.py
trello/models/boards_members.py
trello/models/boards_memberships.py
trello/models/boards_name.py
trello/models/boards_power_ups.py
trello/models/boards_subscribed.py
trello/models/cards.py
trello/models/cards_actions_comments.py
trello/models/cards_attachments.py
trello/models/cards_checklist_check_item.py
trello/models/cards_checklist_check_item_name.py
trello/models/cards_checklist_check_item_pos.py
trello/models/cards_checklist_check_item_state.py
trello/models/cards_checklist_id_checklist_current_check_item.py
trello/models/cards_checklists.py
trello/models/cards_closed.py
trello_sdk-1.0.0.dist-info/licenses/LICENSE
trello_sdk-1.0.0.dist-info/METADATA
trello_sdk-1.0.0.dist-info/WHEEL
trello_sdk-1.0.0.dist-info/top_level.txt
trello_sdk-1.0.0.dist-info/RECORD
